Metadata-Version: 2.1
Name: Nabilkz
Version: 1.2
Summary: An AI package
Author: Nabil Kzez
Author-email: nn2510220@gmail.com
